pswd_auth/__init__.py
pswd_auth/models.py
pswd_auth/pydantic.py
pswd_auth-0.0.5.dist-info/METADATA
pswd_auth-0.0.5.dist-info/WHEEL
pswd_auth-0.0.5.dist-info/top_level.txt
pswd_auth-0.0.5.dist-info/RECORD
